dynamic_host/__init__.py
dynamic_host/apps.py
dynamic_host/conf.py
dynamic_host/helpers.py
dynamic_host/middleware.py
dynamic_host/tests/__init__.py
dynamic_host/tests/test_middleware.py
dynamic_host/tests/test_resolver.py
dynamic_host/tests/test_settings.py
django_dynamic_host-0.0.2.dist-info/LICENCE
django_dynamic_host-0.0.2.dist-info/METADATA
django_dynamic_host-0.0.2.dist-info/WHEEL
django_dynamic_host-0.0.2.dist-info/top_level.txt
django_dynamic_host-0.0.2.dist-info/RECORD
