Metadata-Version: 2.1
Name: django-dynamic-host
Version: 0.0.2
Summary: Django dynamic host helps you validate hostname(origin of client) trying to reach your application dynamically. Django dynamic host helps by-pass the ALLOWED_HOST settings which is restricted to a constant manually added value of hostnames.
Author-email: John Goodnews Osonwa <goodnewsj62@gmail.com>
License: MIT
Classifier: Environment :: Web Environment
Classifier: Operating System :: OS Independent
Classifier: Framework :: Django
Classifier: Programming Language :: Python :: 3
Requires-Python: >=3.7
License-File: LICENCE
Requires-Dist: Django >=3.2
Requires-Dist: importlib-metadata ; python_version >= "3.7"
